memorizing_transformers_pytorch/__init__.py
memorizing_transformers_pytorch/knn_memory.py
memorizing_transformers_pytorch/memorizing_transformers_pytorch.py
memorizing_transformers_pytorch-0.4.1.dist-info/LICENSE
memorizing_transformers_pytorch-0.4.1.dist-info/METADATA
memorizing_transformers_pytorch-0.4.1.dist-info/WHEEL
memorizing_transformers_pytorch-0.4.1.dist-info/top_level.txt
memorizing_transformers_pytorch-0.4.1.dist-info/RECORD
