Metadata-Version: 2.1
Name: memorizing-transformers-pytorch
Version: 0.4.1
Summary: Memorizing Transformer - Pytorch
Home-page: https://github.com/lucidrains/memorizing-transformers-pytorch
Author: Phil Wang
Author-email: lucidrains@gmail.com
License: MIT
Keywords: artificial intelligence,deep learning,transformers,memory,retrieval
Classifier: Development Status :: 4 - Beta
Classifier: Intended Audience :: Developers
Classifier: Topic :: Scientific/Engineering :: Artificial Intelligence
Classifier: License :: OSI Approved :: MIT License
Classifier: Programming Language :: Python :: 3.6
License-File: LICENSE
Requires-Dist: einops (>=0.6)
Requires-Dist: filelock
Requires-Dist: joblib
Requires-Dist: faiss-gpu
Requires-Dist: numpy
Requires-Dist: torch (>=1.6)
